magcopy/__init__.py
magcopy/clipboard.py
magcopy/main.py
magcopy/path.py
magcopy-0.0.3.1.dist-info/LICENSE
magcopy-0.0.3.1.dist-info/METADATA
magcopy-0.0.3.1.dist-info/WHEEL
magcopy-0.0.3.1.dist-info/entry_points.txt
magcopy-0.0.3.1.dist-info/top_level.txt
magcopy-0.0.3.1.dist-info/RECORD
