Metadata-Version: 2.1
Name: magcopy
Version: 0.0.3.1
Summary: magcopy is a command-line utility that simplifies the copy and move operations of files and directories between terminal windows.
Author-email: Adaías Magdiel <eu@adaiasmagdiel.com>
Project-URL: Homepage, https://github.com/AdaiasMagdiel/magcopy
Project-URL: Documentation, https://github.com/AdaiasMagdiel/magcopy/blob/main/README.md
Project-URL: Repository, https://github.com/AdaiasMagdiel/magcopy
Project-URL: Issues, https://github.com/AdaiasMagdiel/magcopy/issues
Keywords: file management,command-line utility,clipboard,copy and move,terminal interaction
Classifier: Development Status :: 4 - Beta
Classifier: Environment :: Console
Classifier: Intended Audience :: Developers
Classifier: Intended Audience :: End Users/Desktop
Classifier: License :: OSI Approved :: MIT License
Classifier: Programming Language :: Python :: 3
Classifier: Programming Language :: Python :: 3.6
Classifier: Programming Language :: Python :: 3.7
Classifier: Programming Language :: Python :: 3.8
Classifier: Programming Language :: Python :: 3.9
Classifier: Programming Language :: Python :: 3.10
Classifier: Programming Language :: Python :: 3.11
Classifier: Programming Language :: Python :: 3.12
Classifier: Programming Language :: Python :: 3.13
Classifier: Topic :: Software Development :: Build Tools
Requires-Python: >=3.6
License-File: LICENSE
